{
  "recentFiles": [
    {
      "basename": "0. 周期性规划",
      "path": "0. 周期性规划.md"
    },
    {
      "basename": "2024-02-26",
      "path": "Daily/2024-02-26.md"
    },
    {
      "basename": "操作系统",
      "path": "Be Yourself/简历/面试题/基础知识/操作系统.md"
    },
    {
      "basename": "面试Checklist",
      "path": "Be Yourself/简历/面试Checklist.md"
    },
    {
      "basename": "2024-02-23",
      "path": "Daily/2024-02-23.md"
    },
    {
      "basename": "2024-02-22",
      "path": "Daily/2024-02-22.md"
    },
    {
      "basename": "202312051508",
      "path": "202312051508.md"
    },
    {
      "basename": "易经",
      "path": "Reading Notes/中国经典/易经.md"
    },
    {
      "basename": "围城",
      "path": "Reading Notes/小说/围城.md"
    },
    {
      "basename": "拜年吉祥话",
      "path": "Be Yourself/其它/拜年吉祥话.md"
    },
    {
      "basename": "Linux 八股文",
      "path": "Be Yourself/简历/面试题/基础知识/Linux 八股文.md"
    },
    {
      "basename": "Golang 熔断限流降级",
      "path": "Coding/Go/深入理解go/Golang 熔断限流降级.md"
    },
    {
      "basename": "算法题目总结",
      "path": "Algorithm/HOT100/算法题目总结.md"
    },
    {
      "basename": "2024-02-05",
      "path": "Daily/2024-02-05.md"
    },
    {
      "basename": "面试题",
      "path": "Be Yourself/简历/面试题.md"
    },
    {
      "basename": "2024-02-01",
      "path": "Daily/2024-02-01.md"
    },
    {
      "basename": "Gin 面试题",
      "path": "Be Yourself/简历/面试题/Go/Gin 面试题.md"
    },
    {
      "basename": "缓存模块之并发编程",
      "path": "Course/极客时间/Golang 实战训练营/缓存模块之并发编程.md"
    },
    {
      "basename": "Go 分布式锁",
      "path": "Coding/Go/深入理解go/Go 分布式锁.md"
    },
    {
      "basename": "业务代码",
      "path": "代码模板/业务代码.md"
    },
    {
      "basename": "病毒触发软件",
      "path": "Be Yourself/简历/面试题/项目总结/病毒触发软件.md"
    },
    {
      "basename": "2024-02-03",
      "path": "Daily/2024-02-03.md"
    },
    {
      "basename": "Go Map 原理",
      "path": "Coding/Go/深入理解go/Go Map 原理.md"
    },
    {
      "basename": "日常实习简历优化",
      "path": "Be Yourself/简历/简历优化/日常实习简历优化.md"
    },
    {
      "basename": "计算机网络",
      "path": "Be Yourself/简历/面试题/基础知识/计算机网络.md"
    },
    {
      "basename": "Go Channel",
      "path": "Coding/Go/深入理解go/Go Channel.md"
    },
    {
      "basename": "2024-01-30",
      "path": "Daily/2024-01-30.md"
    },
    {
      "basename": "2024-01-29",
      "path": "Daily/2024-01-29.md"
    },
    {
      "basename": "Go 初级工程师(面试题)",
      "path": "Be Yourself/简历/面试题/极客时间面试题/Go 初级工程师(面试题).md"
    },
    {
      "basename": "Go 实战训练营(面试题)",
      "path": "Be Yourself/简历/面试题/极客时间面试题/Go 实战训练营(面试题).md"
    },
    {
      "basename": "京东日常实习",
      "path": "实习/京东日常实习.md"
    },
    {
      "basename": "GMP 原理",
      "path": "Coding/Go/深入理解go/GMP 原理.md"
    },
    {
      "basename": "README",
      "path": "Be Yourself/简历/面试题/ES/README.md"
    },
    {
      "basename": "Go 八股文",
      "path": "Coding/Go/Go 八股文.md"
    },
    {
      "basename": "Shell 教程",
      "path": "Coding/Shell/Shell 教程.md"
    },
    {
      "basename": "Coding index",
      "path": "Coding/Coding index.md"
    },
    {
      "basename": "Go 面试题",
      "path": "Be Yourself/简历/面试题/Go/Go 面试题.md"
    },
    {
      "basename": "Go 编程题目",
      "path": "Be Yourself/简历/面试题/Go/Go 编程题目.md"
    },
    {
      "basename": "README",
      "path": "Be Yourself/简历/面试题/校招面试/面试扫盲学习/1_消息队列的面试连环炮/README.md"
    },
    {
      "basename": "字节面试",
      "path": "Be Yourself/简历/面试题/校招面试/面经汇总/2_字节跳动面试总结/字节面试.md"
    },
    {
      "basename": "README",
      "path": "Be Yourself/简历/面试题/校招面试/面经汇总/1_京东面经/README.md"
    },
    {
      "basename": "分布式系统的面试连环炮",
      "path": "Be Yourself/简历/面试题/分布式/分布式系统的面试连环炮.md"
    },
    {
      "basename": "README",
      "path": "Be Yourself/简历/面试题/公众号/046_蘑菇博客Go版部署指南/README.md"
    },
    {
      "basename": "README",
      "path": "Be Yourself/简历/面试题/公众号/014_陌溪在Github网上冲浪时遇到的问题/README.md"
    },
    {
      "basename": "README",
      "path": "Be Yourself/简历/面试题/公众号/007_蘑菇博客前端页面引入矢量图标/README.md"
    },
    {
      "basename": "README",
      "path": "Be Yourself/简历/面试题/公众号/006_年轻人不讲码德,竟然用1核2G服务器来部署蘑菇博客/README.md"
    },
    {
      "basename": "server",
      "path": "Be Yourself/简历/面试题/公众号/006_年轻人不讲码德,竟然用1核2G服务器来部署蘑菇博客/images/server.jpg"
    },
    {
      "basename": "README",
      "path": "Be Yourself/简历/面试题/公众号/002_大型生产事故,开源项目蘑菇博客差点被删库/README.md"
    },
    {
      "basename": "README",
      "path": "Be Yourself/简历/面试题/公众号/001_我是陌溪，很高兴认识大家/README.md"
    },
    {
      "basename": "2024-01-27",
      "path": "Daily/2024-01-27.md"
    }
  ],
  "omittedPaths": [],
  "maxLength": null,
  "openType": "tab"
}