{
  "main": {
    "id": "d574f48e9c26e876",
    "type": "split",
    "children": [
      {
        "id": "9f84aedb9f968bff",
        "type": "tabs",
        "children": [
          {
            "id": "5d8dd044e21f0861",
            "type": "leaf",
            "state": {
              "type": "pdf",
              "state": {
                "file": "Cyber Security/HW/03-信息收集/附赠资料/Nmap使用技巧总结.pdf"
              }
            }
          },
          {
            "id": "4fde78da5911dd20",
            "type": "leaf",
            "state": {
              "type": "pdf",
              "state": {
                "file": "Cyber Security/HW/05-命令执行漏洞/Linux常用命令.pdf"
              }
            }
          },
          {
            "id": "3195ce5752cd74ad",
            "type": "leaf",
            "state": {
              "type": "markdown",
              "state": {
                "file": "Challenge/Habit Challenge/Summary.md",
                "mode": "source",
                "backlinks": false,
                "source": false
              }
            }
          }
        ],
        "currentTab": 2
      },
      {
        "id": "544578fbda1a3916",
        "type": "tabs",
        "children": [
          {
            "id": "e6685c110a4cdb8e",
            "type": "leaf",
            "pinned": true,
            "state": {
              "type": "markdown",
              "state": {
                "file": "Day3/Day3.md",
                "mode": "source",
                "backlinks": false,
                "source": false
              },
              "pinned": true
            }
          },
          {
            "id": "17541c294144c482",
            "type": "leaf",
            "state": {
              "type": "empty",
              "state": {}
            }
          }
        ]
      }
    ],
    "direction": "vertical"
  },
  "left": {
    "id": "9109525faff37552",
    "type": "split",
    "children": [
      {
        "id": "c0dc2db21f59bd0f",
        "type": "tabs",
        "children": [
          {
            "id": "697acbfa6887713c",
            "type": "leaf",
            "state": {
              "type": "file-explorer",
              "state": {
                "sortOrder": "alphabetical"
              }
            }
          },
          {
            "id": "5794a320267150b5",
            "type": "leaf",
            "state": {
              "type": "search",
              "state": {
                "query": "tag:#deeplocker",
                "matchingCase": false,
                "explainSearch": false,
                "collapseAll": false,
                "extraContext": false,
                "sortOrder": "alphabetical"
              }
            }
          },
          {
            "id": "5ecba1e7f0e057ac",
            "type": "leaf",
            "state": {
              "type": "backlink",
              "state": {
                "file": "Day3/Day3.md",
                "collapseAll": false,
                "extraContext": false,
                "sortOrder": "alphabetical",
                "showSearch": false,
                "searchQuery": "",
                "backlinkCollapsed": false,
                "unlinkedCollapsed": true
              }
            }
          },
          {
            "id": "710019ca732354d5",
            "type": "leaf",
            "state": {
              "type": "advanced-tables-toolbar",
              "state": {}
            }
          },
          {
            "id": "33627034220094ce",
            "type": "leaf",
            "state": {
              "type": "tag",
              "state": {
                "sortOrder": "frequency",
                "useHierarchy": false
              }
            }
          },
          {
            "id": "76bb340ba2b85061",
            "type": "leaf",
            "state": {
              "type": "bookmarks",
              "state": {}
            }
          },
          {
            "id": "dd033378146af3f6",
            "type": "leaf",
            "state": {
              "type": "recent-files",
              "state": {}
            }
          },
          {
            "id": "575c93b4864300f2",
            "type": "leaf",
            "state": {
              "type": "file-tree-view",
              "state": {}
            }
          }
        ]
      }
    ],
    "direction": "horizontal",
    "width": 321.51103591918945
  },
  "right": {
    "id": "fcdcb99473c1ab05",
    "type": "split",
    "children": [
      {
        "id": "a179f5a3e4feae61",
        "type": "tabs",
        "children": [
          {
            "id": "811215e87ba12079",
            "type": "leaf",
            "state": {
              "type": "outline",
              "state": {
                "file": "Day3/Day3.md"
              }
            }
          },
          {
            "id": "24ec5dd69d73c45a",
            "type": "leaf",
            "state": {
              "type": "calendar",
              "state": {}
            }
          },
          {
            "id": "5cf2fdffe7792622",
            "type": "leaf",
            "state": {
              "type": "backlink",
              "state": {
                "file": "Day3/Day3.md",
                "collapseAll": true,
                "extraContext": false,
                "sortOrder": "alphabetical",
                "showSearch": true,
                "searchQuery": "",
                "backlinkCollapsed": false,
                "unlinkedCollapsed": false
              }
            }
          },
          {
            "id": "6e89884ae49250e2",
            "type": "leaf",
            "state": {
              "type": "reminder-list",
              "state": {}
            }
          },
          {
            "id": "7732bbfb2e4df86f",
            "type": "leaf",
            "state": {
              "type": "outgoing-link",
              "state": {
                "file": "Day3/Day3.md",
                "linksCollapsed": false,
                "unlinkedCollapsed": true
              }
            }
          },
          {
            "id": "1d9133ca19ac2c35",
            "type": "leaf",
            "state": {
              "type": "todo",
              "state": {}
            }
          }
        ]
      }
    ],
    "direction": "horizontal",
    "width": 363.5,
    "collapsed": true
  },
  "left-ribbon": {
    "hiddenItems": {
      "workbench-obsidian:Workbench": false,
      "switcher:打开快速切换": false,
      "graph:查看关系图谱": false,
      "canvas:新建白板": false,
      "daily-notes:打开/创建今天的日记": false,
      "templates:插入模板": false,
      "command-palette:打开命令面板": false,
      "markdown-importer:打开 Markdown 格式转换器": false,
      "workspaces:管理工作区布局": false,
      "table-editor-obsidian:Advanced Tables Toolbar": false,
      "obsidian-excalidraw-plugin:新建 Excalidraw 绘图": false,
      "obsidian-hypothesis-plugin:Sync your hypothesis highlights": false,
      "random-note:开始漫游笔记": false,
      "templater-obsidian:Templater": false,
      "audio-recorder:开始/结束录音": false,
      "file-tree-alternative:File Tree Alternative Plugin": false
    }
  },
  "active": "e6685c110a4cdb8e",
  "lastOpenFiles": [
    "Day3/Day3.md",
    "Challenge/Habit Challenge/Summary.md",
    "Challenge/Habit Challenge/Running.md",
    "Challenge/Habit Challenge/Morning Reading.md",
    "Challenge/Habit Challenge/Go Pro.md",
    "Challenge/Habit Challenge/English Practice.md",
    "Challenge/Habit Challenge/Algorithm.md",
    "Cyber Security/HW/05-命令执行漏洞/Linux常用命令.pdf",
    "Cyber Security/HW/04-SQL注入漏洞/SQL注入-中-课件.pdf",
    "Cyber Security/HW/04-SQL注入漏洞/SQL注入-下-课件.pdf",
    "Cyber Security/HW/04-SQL注入漏洞/SQL注入-上-课件.pdf",
    "Cyber Security/HW/03-信息收集/nmap 使用.md",
    "Cyber Security/HW/03-信息收集/课件笔记/3.6-CDN指纹识别-脑图笔记.pdf",
    "Cyber Security/HW/03-信息收集/课件笔记/3.5-CMS指纹识别-脑图笔记.pdf",
    "Cyber Security/HW/03-信息收集/课件笔记/3.4-端口服务信息-脑图笔记.pdf",
    "Cyber Security/HW/03-信息收集/课件笔记/3.3-IP信息-课件.pdf",
    "Cyber Security/HW/03-信息收集/课件笔记/3.2-域名信息-脑图笔记.png",
    "Cyber Security/HW/03-信息收集/课件笔记/3.2-域名信息-课件.pdf",
    "Cyber Security/HW/03-信息收集/课件笔记/3.1-信息收集概览-PPT.pdf",
    "Algorithm/数据结构/Lists.md",
    "Eassay/随想.md",
    "Algorithm/Github/Github 资源搜集.md",
    "Cyber Security/Red Team/基础设施构建/Hacker Tools/nmap.md",
    "Cyber Security/HW/如何参加 HW.md",
    "Algorithm/数据结构/数据结构.md",
    "Coding/Go/Go Pro/Go 语言基础.md",
    "Algorithm/算法总结.md",
    "Algorithm/Algorithm index.md",
    "Coding/Go/Third-party library/portaudio/portaudio.md",
    "Coding/Go/Third-party library/go audio/basic go audio.md",
    "Coding/C&CPP/C 开发环境搭建.md",
    "Basic/Unicode 与 utf-8.md",
    "Coding/Go/Third-party library/gocv/gocv.Mat.md",
    "Coding/Go/其他问题/绝对路径和相对路径问题.md",
    "Website/serengildeepface_models Pre-trained models for deepface python library.md",
    "Website/1.1 Go语言创世纪 · Go语言高级编程 (1).md",
    "Website/1.1 Go语言创世纪 · Go语言高级编程.md",
    "Coding/Go/Go Pro/Snipaste/Pasted image 20230606214652.png",
    "Cyber Security/HW/02-HTTP&Burp课程资料/2.1-HTTP/常见请求头和响应头.png",
    "Cyber Security/HW/03-信息收集/课件笔记/3.3-IP信息-脑图笔记.png",
    "PDFS/CCNA1-10.3.1.2-Packet-Tracer-Explore-a-Network.webp",
    "Coding/Python/爬虫/Snipaste/Pasted image 20230606163729.png",
    "Coding/Python/爬虫/Snipaste/Pasted image 20230606162002.png",
    "Coding/Go/Third-party library/fyne/Go 每日一库之 fyne - 大俊的博客_files/fyne27.png",
    "Coding/Go/Third-party library/fyne/Go 每日一库之 fyne - 大俊的博客_files/wxgzh8.jpg",
    "Coding/Go/Third-party library/fyne/Go 每日一库之 fyne - 大俊的博客_files/fyne1.png",
    "AI/未命名.canvas",
    "Cyber Security/Red Team/基础设施构建/Hacker Tools/未命名.canvas",
    "未命名.canvas",
    "未命名 1.canvas"
  ]
}