{
  "main": {
    "id": "d574f48e9c26e876",
    "type": "split",
    "children": [
      {
        "id": "9f84aedb9f968bff",
        "type": "tabs",
        "children": [
          {
            "id": "e6685c110a4cdb8e",
            "type": "leaf",
            "pinned": true,
            "state": {
              "type": "markdown",
              "state": {
                "file": "Day3/Day3.md",
                "mode": "source",
                "backlinks": false,
                "source": false
              },
              "pinned": true
            }
          },
          {
            "id": "444eedf933a71967",
            "type": "leaf",
            "pinned": true,
            "state": {
              "type": "markdown",
              "state": {
                "file": "Eassay/随想.md",
                "mode": "source",
                "backlinks": false,
                "source": false
              },
              "pinned": true
            }
          },
          {
            "id": "18fe31c6a7715ddf",
            "type": "leaf",
            "state": {
              "type": "markdown",
              "state": {
                "file": "Resume/Resume.md",
                "mode": "source",
                "backlinks": false,
                "source": false
              }
            }
          },
          {
            "id": "ccf1db40f3318ed0",
            "type": "leaf",
            "state": {
              "type": "markdown",
              "state": {
                "file": "Cyber Security/Deeplocker/deeplocker backend summary.md",
                "mode": "source",
                "backlinks": false,
                "source": false
              }
            }
          }
        ]
      }
    ],
    "direction": "vertical"
  },
  "left": {
    "id": "9109525faff37552",
    "type": "split",
    "children": [
      {
        "id": "c0dc2db21f59bd0f",
        "type": "tabs",
        "children": [
          {
            "id": "697acbfa6887713c",
            "type": "leaf",
            "state": {
              "type": "file-explorer",
              "state": {
                "sortOrder": "alphabetical"
              }
            }
          },
          {
            "id": "5794a320267150b5",
            "type": "leaf",
            "state": {
              "type": "search",
              "state": {
                "query": "tag:#七、什么是蓝队",
                "matchingCase": false,
                "explainSearch": false,
                "collapseAll": false,
                "extraContext": false,
                "sortOrder": "alphabetical"
              }
            }
          },
          {
            "id": "5ecba1e7f0e057ac",
            "type": "leaf",
            "state": {
              "type": "backlink",
              "state": {
                "file": "Day3/Day3.md",
                "collapseAll": false,
                "extraContext": false,
                "sortOrder": "alphabetical",
                "showSearch": false,
                "searchQuery": "",
                "backlinkCollapsed": false,
                "unlinkedCollapsed": true
              }
            }
          },
          {
            "id": "710019ca732354d5",
            "type": "leaf",
            "state": {
              "type": "advanced-tables-toolbar",
              "state": {}
            }
          },
          {
            "id": "33627034220094ce",
            "type": "leaf",
            "state": {
              "type": "tag",
              "state": {
                "sortOrder": "frequency",
                "useHierarchy": false
              }
            }
          },
          {
            "id": "76bb340ba2b85061",
            "type": "leaf",
            "state": {
              "type": "bookmarks",
              "state": {}
            }
          },
          {
            "id": "dd033378146af3f6",
            "type": "leaf",
            "state": {
              "type": "recent-files",
              "state": {}
            }
          },
          {
            "id": "575c93b4864300f2",
            "type": "leaf",
            "state": {
              "type": "file-tree-view",
              "state": {}
            }
          }
        ]
      }
    ],
    "direction": "horizontal",
    "width": 321.51103591918945
  },
  "right": {
    "id": "fcdcb99473c1ab05",
    "type": "split",
    "children": [
      {
        "id": "a179f5a3e4feae61",
        "type": "tabs",
        "children": [
          {
            "id": "811215e87ba12079",
            "type": "leaf",
            "state": {
              "type": "outline",
              "state": {
                "file": "Day3/Day3.md"
              }
            }
          },
          {
            "id": "24ec5dd69d73c45a",
            "type": "leaf",
            "state": {
              "type": "calendar",
              "state": {}
            }
          },
          {
            "id": "5cf2fdffe7792622",
            "type": "leaf",
            "state": {
              "type": "backlink",
              "state": {
                "file": "Day3/Day3.md",
                "collapseAll": true,
                "extraContext": false,
                "sortOrder": "alphabetical",
                "showSearch": true,
                "searchQuery": "",
                "backlinkCollapsed": false,
                "unlinkedCollapsed": false
              }
            }
          },
          {
            "id": "6e89884ae49250e2",
            "type": "leaf",
            "state": {
              "type": "reminder-list",
              "state": {}
            }
          },
          {
            "id": "7732bbfb2e4df86f",
            "type": "leaf",
            "state": {
              "type": "outgoing-link",
              "state": {
                "file": "Day3/Day3.md",
                "linksCollapsed": false,
                "unlinkedCollapsed": true
              }
            }
          },
          {
            "id": "1d9133ca19ac2c35",
            "type": "leaf",
            "state": {
              "type": "todo",
              "state": {}
            }
          }
        ]
      }
    ],
    "direction": "horizontal",
    "width": 363.5,
    "collapsed": true
  },
  "left-ribbon": {
    "hiddenItems": {
      "workbench-obsidian:Workbench": false,
      "switcher:打开快速切换": false,
      "graph:查看关系图谱": false,
      "canvas:新建白板": false,
      "daily-notes:打开/创建今天的日记": false,
      "templates:插入模板": false,
      "command-palette:打开命令面板": false,
      "markdown-importer:打开 Markdown 格式转换器": false,
      "workspaces:管理工作区布局": false,
      "table-editor-obsidian:Advanced Tables Toolbar": false,
      "obsidian-excalidraw-plugin:新建 Excalidraw 绘图": false,
      "obsidian-hypothesis-plugin:Sync your hypothesis highlights": false,
      "random-note:开始漫游笔记": false,
      "templater-obsidian:Templater": false,
      "audio-recorder:开始/结束录音": false,
      "file-tree-alternative:File Tree Alternative Plugin": false,
      "obsidian-statusbar-pomo:Start pomodoro": false,
      "periodic-notes:Open today": false
    }
  },
  "active": "e6685c110a4cdb8e",
  "lastOpenFiles": [
    "Eassay/随想.md",
    "Resume/Resume.md",
    "Cyber Security/Deeplocker/deeplocker backend summary.md",
    "Day3/Day3.md",
    "Cyber Security/Deeplocker/deeplocker 信息整合(memos).md",
    "Cyber Security/调研/Deeplocker.md",
    "Resume/Snipaste/Pasted image 20230609104940.png",
    "Resume/Snipaste",
    "Resume/招聘网站/领英职场.md",
    "Resume/招聘网站/实习僧.md",
    "Resume/招聘网站/内推网.md",
    "Resume/招聘网站/电商人才.md",
    "Resume/招聘网站/拉勾网.md",
    "Resume/招聘网站/当地的人才网.md",
    "Resume/招聘网站/猎聘网.md",
    "Resume/招聘网站/前程无忧.md",
    "Resume/招聘网站/智联招聘.md",
    "Resume/招聘网站/各厂的招聘官网.md",
    "Resume/招聘网站/校招.md",
    "Resume/招聘网站/Boss直聘.md",
    "Resume/招聘网站/牛客网.md",
    "Resume/Resume index.md",
    "Resume/招聘网站",
    "Resume/未命名.md",
    "Eassay/企划书/企划书.md",
    "Cyber Security/HW/19-安全设备和面试/面试.pdf",
    "Coding/Go/Third-party library/gocv/gocv.Show.md",
    "Coding/Go/Third-party library/gocv/gocv.Mat.md",
    "Life/活动/准备一下去安全公司需要问的问题.md",
    "Life/活动/GopherChina2023.md",
    "Cyber Security/HW/19-安全设备和面试/常见安全设备.pdf",
    "Cyber Security/HW/18-入侵排查/windows排查.pdf",
    "Cyber Security/HW/18-入侵排查/Linux排查.pdf",
    "Cyber Security/HW/17-内网渗透-课件/NTML和LM哈希.pdf",
    "Cyber Security/HW/17-内网渗透-课件/IPC横向.pdf",
    "Cyber Security/HW/17-内网渗透-课件/抓取密码.pdf",
    "Cyber Security/HW/17-内网渗透-课件/域内信息收集.pdf",
    "Cyber Security/HW/03-信息收集/课件笔记/3.3-IP信息-脑图笔记.png",
    "Cyber Security/HW/03-信息收集/课件笔记/3.2-域名信息-脑图笔记.png",
    "Cyber Security/HW/01-HW介绍/Snipaste/Pasted image 20230608084237.png",
    "Cyber Security/HW/01-HW介绍/Snipaste/Pasted image 20230608083329.png",
    "Cyber Security/HW/Snipaste/Pasted image 20230608083006.png",
    "Cyber Security/HW/Snipaste/Pasted image 20230608082959.png",
    "Cyber Security/HW/Snipaste/Pasted image 20230608082946.png",
    "Cyber Security/HW/Snipaste/Pasted image 20230608082935.png",
    "Cyber Security/HW/Snipaste/Pasted image 20230608082927.png",
    "AI/未命名.canvas",
    "Cyber Security/Red Team/基础设施构建/Hacker Tools/未命名.canvas",
    "未命名.canvas",
    "未命名 1.canvas"
  ]
}